{
  "records": [
    {
      "id": 8721,
      "quote": "We must accept finite disappointment, but we must never lose infinite hope.",
      "author": "Martin Luther King"
    },
    {
      "id": 5779,
      "quote": "Use what you’ve been through as fuel, believe in yourself and be unstoppable!",
      "author": "Yvonne Pierre"
    },
    {
      "id": 3406,
      "quote": "To succeed, you have to do something and be very bad at it for a while. You have to look bad before you can look really good.",
      "author": "Barbara DeAngelis"
    },
    {
      "quote": "Never trust a man with a neck tatoo",
      "author": "Uncle Steve",
      "id": 1400
    },
    {
      "quote": "You'll never see a hurst pulling a Uhaul",
      "author": "Les Brown",
      "id": 1263
    },
    {
      "quote": "You'll never see a hurst pulling a Uhaul",
      "author": "Jim Rohn",
      "id": 3790
    },
    {
      "quote": "You'll never see a hurst pulling a Uhaul",
      "author": "Zig Ziggler",
      "id": 7746
    },
    {
      "quote": "You'll never see a hurst pulling a Uhaul",
      "author": "Bo Diddly",
      "id": 5998
    },
    {
      "quote": "You'll never see a hurst pulling a Uhaul",
      "author": "Johnnyt Rocket",
      "id": 9724
    },
    {
      "quote": "You'll never see a hurst pulling a Uhaul",
      "author": "Johnny Rocket",
      "id": 6550
    },
    {
      "quote": "Do the things that scare you the most",
      "author": "Unkown",
      "id": 522
    },
    {
      "quote": "That what you fear the most",
      "author": "Pearl Jam",
      "id": 1025
    },
    {
      "quote": "Spread more kindness",
      "author": "Unkown",
      "id": 1788
    },
    {
      "quote": "Want what you have",
      "author": "Jimmy Buffett",
      "id": 6660
    }
  ]
}